LICENSE.txt
README.md
setup.cfg
setup.py
octobus/__init__.py
octobus/base.py
octobus.egg-info/PKG-INFO
octobus.egg-info/SOURCES.txt
octobus.egg-info/dependency_links.txt
octobus.egg-info/not-zip-safe
octobus.egg-info/requires.txt
octobus.egg-info/top_level.txt
octobus/utils/__init__.py
tests/__init__.py
tests/test_octopus.py