Metadata-Version: 1.2
Name: octobus
Version: 0.1.1
Summary: A python module for bioinformatics to organize, manage, and package omics datasets, serving as data portal for modeling.
Home-page: https://github.com/haokui/octobus
Author: Haokui Zhou, Shuo Chen, Xilan Yang
Author-email: haokui.zhou@gmail.com
License: BSD 3-Clause License
Download-URL: https://github.com/haokui/octobus/archive/refs/tags/v0.1.1.tar.gz
Platform: UNKNOWN
Classifier: Development Status :: 2 - Pre-Alpha
Classifier: Intended Audience :: Developers
Classifier: License :: OSI Approved :: BSD License
Classifier: Natural Language :: English
Classifier: Programming Language :: Python :: 3
Classifier: Programming Language :: Python :: 3.7
Classifier: Programming Language :: Python :: 3.8
Classifier: Programming Language :: Python :: 3.9
Requires-Python: >=3.7
